setup.py
t_process/__init__.py
t_process.egg-info/PKG-INFO
t_process.egg-info/SOURCES.txt
t_process.egg-info/dependency_links.txt
t_process.egg-info/top_level.txt
t_process.egg-info/zip-safe