Metadata-Version: 1.0
Name: t-process
Version: 0.1
Summary: T process library
Home-page: https://gitlab.com/ddmello/lib/python/t_process.git
Author: Darrin D'Mello
Author-email: darrin.dmello@gmail.com
License: MIT
Platform: UNKNOWN
